{
	"id": "b67d828d-97f0-4491-b055-ce75ca789d7a",
	"name": "Env_Group_33",
	"values": [
		{
			"key": "url",
			"value": "http://162.55.220.72:5005",
			"type": "default",
			"enabled": true
		},
		{
			"key": "token",
			"value": "",
			"type": "default",
			"enabled": true
		},
		{
			"key": "variable_key",
			"value": "",
			"type": "any",
			"enabled": true
		}
	],
	"_postman_variable_scope": "environment",
	"_postman_exported_at": "2023-03-13T20:47:43.357Z",
	"_postman_exported_using": "Postman/10.11.1"
}